aifenlei/__init__.py
aifenlei/classification_assistant.py
aifenlei-1.0.0.dist-info/METADATA
aifenlei-1.0.0.dist-info/WHEEL
aifenlei-1.0.0.dist-info/entry_points.txt
aifenlei-1.0.0.dist-info/top_level.txt
aifenlei-1.0.0.dist-info/RECORD
