Metadata-Version: 2.4
Name: aifenlei
Version: 1.0.0
Summary: 分类选择辅助工具
Home-page: https://github.com/example/aifenlei
Author: sysucai
Author-email: 411703730@qq.com
Classifier: Programming Language :: Python :: 3
Classifier: Programming Language :: Python :: 3.7
Classifier: Programming Language :: Python :: 3.8
Classifier: Programming Language :: Python :: 3.9
Classifier: Programming Language :: Python :: 3.10
Classifier: Programming Language :: Python :: 3.11
Classifier: License :: OSI Approved :: MIT License
Classifier: Operating System :: OS Independent
Classifier: Intended Audience :: Science/Research
Classifier: Topic :: Scientific/Engineering
Classifier: Topic :: Utilities
Requires-Dist: pandas>=1.3.0
Requires-Dist: openpyxl>=3.0.0
Requires-Dist: tksheet>=6.0.0
Requires-Dist: requests>=2.25.0
